pinet/__init__.py
pinet/dataclasses.py
pinet/equilibration.py
pinet/project.py
pinet/constraints/__init__.py
pinet/constraints/affine_equality.py
pinet/constraints/affine_inequality.py
pinet/constraints/base.py
pinet/constraints/box.py
pinet/constraints/constraint_parser.py
pinet/solver/__init__.py
pinet/solver/admm.py
pinet_hcnn-0.1.0.dist-info/licenses/LICENSE
pinet_hcnn-0.1.0.dist-info/METADATA
pinet_hcnn-0.1.0.dist-info/WHEEL
pinet_hcnn-0.1.0.dist-info/top_level.txt
pinet_hcnn-0.1.0.dist-info/RECORD
