Metadata-Version: 2.4
Name: pinet-hcnn
Version: 0.1.0
Summary: A differentiable orthogonal projection layer for training hard-constrained neural networks.
Author-email: Panagiotis Grontas <pgrontas@control.ee.ethz.ch>, Antonio Terpin <aterpin@ethz.ch>
License:                                  Apache License
Project-URL: Homepage, https://github.com/antonioterpin/pinet
Classifier: Programming Language :: Python :: 3
Classifier: License :: OSI Approved :: MIT License
Classifier: Operating System :: OS Independent
License-File: LICENSE
Requires-Dist: jax>=0.6.2
Requires-Dist: tqdm>=4.67.1
Requires-Dist: h5py>=3.13.0
Requires-Dist: ruamel.yaml>=0.18.10
Requires-Dist: imageio>=2.37.0
Requires-Dist: matplotlib>=3.10.1
Requires-Dist: optax>=0.2.4
Requires-Dist: flax>=0.10.2
Requires-Dist: cvxpy>=1.6.6
Requires-Dist: torch>=2.6.0
Requires-Dist: cvxpylayers>=0.1.9
Requires-Dist: jaxopt>=0.8.5
Requires-Dist: wandb>=0.20.1
Provides-Extra: dev
Requires-Dist: snowballstemmer==2.2.0; extra == "dev"
Requires-Dist: pre_commit==4.0.1; extra == "dev"
Requires-Dist: pytest-cov; extra == "dev"
Requires-Dist: tomli; extra == "dev"
Provides-Extra: cuda12
Requires-Dist: jax[cuda12_pip]>=0.6.2; extra == "cuda12"
Dynamic: license-file
